{
  "annotations": {
    "list": [
      {
        "builtIn": 1,
        "datasource": {"type": "grafana", "uid": "-- Grafana --"},
        "enable": true,
        "hide": true,
        "iconColor": "rgba(0, 211, 255, 1)",
        "name": "Annotations & Alerts",
        "target": {"limit": 100, "matchAny": false, "tags": [], "type": "dashboard"},
        "type": "dashboard"
      }
    ]
  },
  "editable": true,
  "fiscalYearStartMonth": 0,
  "graphTooltip": 0,
  "id": null,
  "links": [],
  "panels": [
    {
      "datasource": {"type": "prometheus", "uid": "Prometheus"},
      "fieldConfig": {
        "defaults": {
          "color": {"mode": "thresholds"},
          "mappings": [
            {"options": {"0": {"text": "DOWN"}, "1": {"text": "UP"}}, "type": "value"}
          ],
          "thresholds": {
            "mode": "absolute",
            "steps": [
              {"color": "red", "value": null},
              {"color": "green", "value": 1}
            ]
          }
        },
        "overrides": []
      },
      "gridPos": {"h": 8, "w": 24, "x": 0, "y": 0},
      "id": 1,
      "options": {
        "colorMode": "background",
        "graphMode": "none",
        "justifyMode": "auto",
        "orientation": "horizontal",
        "reduceOptions": {"calcs": ["lastNotNull"], "fields": "", "values": false},
        "showPercentChange": false,
        "textMode": "auto",
        "wideLayout": true
      },
      "pluginVersion": "11.2.0",
      "targets": [
        {
          "datasource": {"type": "prometheus", "uid": "Prometheus"},
          "editorMode": "code",
          "expr": "probe_success{job=\"finance-http-health\"}",
          "legendFormat": "{{instance}}",
          "range": true,
          "refId": "A"
        }
      ],
      "title": "Application service health",
      "type": "stat"
    },
    {
      "datasource": {"type": "prometheus", "uid": "Prometheus"},
      "fieldConfig": {
        "defaults": {"unit": "s"},
        "overrides": []
      },
      "gridPos": {"h": 8, "w": 12, "x": 0, "y": 8},
      "id": 2,
      "options": {
        "legend": {"calcs": [], "displayMode": "list", "placement": "bottom", "showLegend": true},
        "tooltip": {"mode": "single", "sort": "none"}
      },
      "targets": [
        {
          "datasource": {"type": "prometheus", "uid": "Prometheus"},
          "editorMode": "code",
          "expr": "probe_duration_seconds{job=\"finance-http-health\"}",
          "legendFormat": "{{instance}}",
          "range": true,
          "refId": "A"
        }
      ],
      "title": "Health-check response time",
      "type": "timeseries"
    },
    {
      "datasource": {"type": "prometheus", "uid": "Prometheus"},
      "fieldConfig": {
        "defaults": {
          "color": {"mode": "thresholds"},
          "mappings": [
            {"options": {"0": {"text": "DOWN"}, "1": {"text": "UP"}}, "type": "value"}
          ],
          "thresholds": {
            "mode": "absolute",
            "steps": [
              {"color": "red", "value": null},
              {"color": "green", "value": 1}
            ]
          }
        },
        "overrides": []
      },
      "gridPos": {"h": 8, "w": 12, "x": 12, "y": 8},
      "id": 3,
      "options": {
        "colorMode": "background",
        "graphMode": "none",
        "justifyMode": "auto",
        "orientation": "horizontal",
        "reduceOptions": {"calcs": ["lastNotNull"], "fields": "", "values": false},
        "showPercentChange": false,
        "textMode": "auto",
        "wideLayout": true
      },
      "pluginVersion": "11.2.0",
      "targets": [
        {
          "datasource": {"type": "prometheus", "uid": "Prometheus"},
          "editorMode": "code",
          "expr": "probe_success{job=\"finance-tcp-health\"}",
          "legendFormat": "{{instance}}",
          "range": true,
          "refId": "A"
        }
      ],
      "title": "Infrastructure health",
      "type": "stat"
    },
    {
      "datasource": {"type": "prometheus", "uid": "Prometheus"},
      "fieldConfig": {
        "defaults": {"unit": "percentunit"},
        "overrides": []
      },
      "gridPos": {"h": 8, "w": 12, "x": 0, "y": 16},
      "id": 4,
      "options": {
        "legend": {"calcs": [], "displayMode": "list", "placement": "bottom", "showLegend": true},
        "tooltip": {"mode": "single", "sort": "none"}
      },
      "targets": [
        {
          "datasource": {"type": "prometheus", "uid": "Prometheus"},
          "editorMode": "code",
          "expr": "sum(rate(container_cpu_usage_seconds_total{name!=\"\"}[1m])) by (name)",
          "legendFormat": "{{name}}",
          "range": true,
          "refId": "A"
        }
      ],
      "title": "Container CPU usage",
      "type": "timeseries"
    },
    {
      "datasource": {"type": "prometheus", "uid": "Prometheus"},
      "fieldConfig": {
        "defaults": {"unit": "bytes"},
        "overrides": []
      },
      "gridPos": {"h": 8, "w": 12, "x": 12, "y": 16},
      "id": 5,
      "options": {
        "legend": {"calcs": [], "displayMode": "list", "placement": "bottom", "showLegend": true},
        "tooltip": {"mode": "single", "sort": "none"}
      },
      "targets": [
        {
          "datasource": {"type": "prometheus", "uid": "Prometheus"},
          "editorMode": "code",
          "expr": "container_memory_usage_bytes{name!=\"\"}",
          "legendFormat": "{{name}}",
          "range": true,
          "refId": "A"
        }
      ],
      "title": "Container memory usage",
      "type": "timeseries"
    },
    {
      "datasource": {"type": "loki", "uid": "Loki"},
      "gridPos": {"h": 10, "w": 24, "x": 0, "y": 24},
      "id": 6,
      "options": {
        "dedupStrategy": "none",
        "enableLogDetails": true,
        "prettifyLogMessage": false,
        "showCommonLabels": false,
        "showLabels": false,
        "showTime": true,
        "sortOrder": "Descending",
        "wrapLogMessage": true
      },
      "targets": [
        {
          "datasource": {"type": "loki", "uid": "Loki"},
          "editorMode": "code",
          "expr": "{job=\"docker-containers\"}",
          "queryType": "range",
          "refId": "A"
        }
      ],
      "title": "Container logs",
      "type": "logs"
    }
  ],
  "refresh": "10s",
  "schemaVersion": 39,
  "tags": ["finance-tracker", "monitoring"],
  "templating": {"list": []},
  "time": {"from": "now-30m", "to": "now"},
  "timepicker": {},
  "timezone": "browser",
  "title": "Finance Tracker Overview",
  "uid": "finance-tracker-overview",
  "version": 1,
  "weekStart": ""
}
